[
    {"date": "2025-01-01", "usd": "18.4791", "eur": "19.3106", "rub": "0.1713", "ron": "3.8805", "uah": "0.4392"},
    {"date": "2025-01-02", "usd": "18.4050", "eur": "19.1559", "rub": "0.1696", "ron": "3.8510", "uah": "0.4376"},
    {"date": "2025-01-03", "usd": "18.5817", "eur": "19.1912", "rub": "0.1687", "ron": "3.8581", "uah": "0.4410"},
    {"date": "2025-01-04", "usd": "18.5817", "eur": "19.1912", "rub": "0.1687", "ron": "3.8581", "uah": "0.4410"},
    {"date": "2025-01-05", "usd": "18.5817", "eur": "19.1912", "rub": "0.1687", "ron": "3.8581", "uah": "0.4410"},
    {"date": "2025-01-06", "usd": "18.6117", "eur": "19.1700", "rub": "0.1678", "ron": "3.8532", "uah": "0.4417"},
    {"date": "2025-01-07", "usd": "18.6117", "eur": "19.1700", "rub": "0.1678", "ron": "3.8532", "uah": "0.4417"},
    {"date": "2025-01-08", "usd": "18.6117", "eur": "19.1700", "rub": "0.1678", "ron": "3.8532", "uah": "0.4417"},
    {"date": "2025-01-09", "usd": "18.4020", "eur": "19.1767", "rub": "0.1711", "ron": "3.8549", "uah": "0.4356"},
    {"date": "2025-01-10", "usd": "18.6674", "eur": "19.2293", "rub": "0.1817", "ron": "3.8667", "uah": "0.4407"},
    {"date": "2025-01-11", "usd": "18.6674", "eur": "19.2293", "rub": "0.1817", "ron": "3.8667", "uah": "0.4407"},
    {"date": "2025-01-12", "usd": "18.6674", "eur": "19.2293", "rub": "0.1817", "ron": "3.8667", "uah": "0.4407"},
    {"date": "2025-01-13", "usd": "18.6915", "eur": "19.2541", "rub": "0.1831", "ron": "3.8719", "uah": "0.4421"},
    {"date": "2025-01-14", "usd": "18.9202", "eur": "19.2929", "rub": "0.1841", "ron": "3.8795", "uah": "0.4464"},
    {"date": "2025-01-15", "usd": "18.8109", "eur": "19.2906", "rub": "0.1825", "ron": "3.8775", "uah": "0.4451"},
    {"date": "2025-01-16", "usd": "18.7452", "eur": "19.3113", "rub": "0.1826", "ron": "3.8820", "uah": "0.4434"},
    {"date": "2025-01-17", "usd": "18.7918", "eur": "19.3386", "rub": "0.1836", "ron": "3.8870", "uah": "0.4458"},
    {"date": "2025-01-18", "usd": "18.7918", "eur": "19.3386", "rub": "0.1836", "ron": "3.8870", "uah": "0.4458"},
    {"date": "2025-01-19", "usd": "18.7918", "eur": "19.3386", "rub": "0.1836", "ron": "3.8870", "uah": "0.4458"},
    {"date": "2025-01-20", "usd": "18.7682", "eur": "19.3350", "rub": "0.1833", "ron": "3.8853", "uah": "0.4458"},
    {"date": "2025-01-21", "usd": "18.7200", "eur": "19.3284", "rub": "0.1838", "ron": "3.8839", "uah": "0.4435"},
    {"date": "2025-01-22", "usd": "18.6824", "eur": "19.3419", "rub": "0.1880", "ron": "3.8864", "uah": "0.4434"},
    {"date": "2025-01-23", "usd": "18.5647", "eur": "19.3853", "rub": "0.1881", "ron": "3.8952", "uah": "0.4419"},
    {"date": "2025-01-24", "usd": "18.6406", "eur": "19.3955", "rub": "0.1876", "ron": "3.8976", "uah": "0.4439"},
    {"date": "2025-01-25", "usd": "18.6406", "eur": "19.3955", "rub": "0.1876", "ron": "3.8976", "uah": "0.4439"},
    {"date": "2025-01-26", "usd": "18.6406", "eur": "19.3955", "rub": "0.1876", "ron": "3.8976", "uah": "0.4439"},
    {"date": "2025-01-27", "usd": "18.4996", "eur": "19.3987", "rub": "0.1888", "ron": "3.8987", "uah": "0.4414"},
    {"date": "2025-01-28", "usd": "18.4591", "eur": "19.4042", "rub": "0.1910", "ron": "3.9005", "uah": "0.4397"},
    {"date": "2025-01-29", "usd": "18.6157", "eur": "19.4078", "rub": "0.1891", "ron": "3.9011", "uah": "0.4427"},
    {"date": "2025-01-30", "usd": "18.6392", "eur": "19.3866", "rub": "0.1894", "ron": "3.8964", "uah": "0.4447"},
    {"date": "2025-01-31", "usd": "18.6764", "eur": "19.4122", "rub": "0.1905", "ron": "3.9013", "uah": "0.4470"},
    {"date": "2025-02-01", "usd": "18.6764", "eur": "19.4122", "rub": "0.1905", "ron": "3.9013", "uah": "0.4470"},
    {"date": "2025-02-02", "usd": "18.6764", "eur": "19.4122", "rub": "0.1905", "ron": "3.9013", "uah": "0.4470"},
    {"date": "2025-02-03", "usd": "18.7208", "eur": "19.4228", "rub": "0.1901", "ron": "3.9028", "uah": "0.4489"},
    {"date": "2025-02-04", "usd": "18.9231", "eur": "19.4009", "rub": "0.1896", "ron": "3.8983", "uah": "0.4525"},
    {"date": "2025-02-05", "usd": "18.7656", "eur": "19.3717", "rub": "0.1881", "ron": "3.8922", "uah": "0.4495"},
    {"date": "2025-02-06", "usd": "18.6334", "eur": "19.4067", "rub": "0.1902", "ron": "3.8996", "uah": "0.4478"},
    {"date": "2025-02-07", "usd": "18.7535", "eur": "19.4333", "rub": "0.1938", "ron": "3.9050", "uah": "0.4524"},
    {"date": "2025-02-08", "usd": "18.7535", "eur": "19.4333", "rub": "0.1938", "ron": "3.9050", "uah": "0.4524"},
    {"date": "2025-02-09", "usd": "18.7535", "eur": "19.4333", "rub": "0.1938", "ron": "3.9050", "uah": "0.4524"},
    {"date": "2025-02-10", "usd": "18.7153", "eur": "19.4302", "rub": "0.1927", "ron": "3.9044", "uah": "0.4516"},
    {"date": "2025-02-11", "usd": "18.8216", "eur": "19.4295", "rub": "0.1938", "ron": "3.9041", "uah": "0.4523"},
    {"date": "2025-02-12", "usd": "18.8241", "eur": "19.4284", "rub": "0.1969", "ron": "3.9040", "uah": "0.4514"},
    {"date": "2025-02-13", "usd": "18.7296", "eur": "19.4338", "rub": "0.1992", "ron": "3.9050", "uah": "0.4479"},
    {"date": "2025-02-14", "usd": "18.7052", "eur": "19.4572", "rub": "0.2049", "ron": "3.9091", "uah": "0.4479"},
    {"date": "2025-02-15", "usd": "18.7052", "eur": "19.4572", "rub": "0.2049", "ron": "3.9091", "uah": "0.4479"},
    {"date": "2025-02-16", "usd": "18.7052", "eur": "19.4572", "rub": "0.2049", "ron": "3.9091", "uah": "0.4479"},
    {"date": "2025-02-17", "usd": "18.6030", "eur": "19.4718", "rub": "0.2039", "ron": "3.9124", "uah": "0.4470"},
    {"date": "2025-02-18", "usd": "18.5881", "eur": "19.4822", "rub": "0.2026", "ron": "3.9144", "uah": "0.4477"},
    {"date": "2025-02-19", "usd": "18.6333", "eur": "19.4960", "rub": "0.2037", "ron": "3.9172", "uah": "0.4480"},
    {"date": "2025-02-20", "usd": "18.6944", "eur": "19.4870", "rub": "0.2079", "ron": "3.9151", "uah": "0.4482"},
    {"date": "2025-02-21", "usd": "18.6797", "eur": "19.4941", "rub": "0.2117", "ron": "3.9167", "uah": "0.4486"},
    {"date": "2025-02-22", "usd": "18.6797", "eur": "19.4941", "rub": "0.2117", "ron": "3.9167", "uah": "0.4486"},
    {"date": "2025-02-23", "usd": "18.6797", "eur": "19.4941", "rub": "0.2117", "ron": "3.9167", "uah": "0.4486"},
    {"date": "2025-02-24", "usd": "18.6306", "eur": "19.5062", "rub": "0.2095", "ron": "3.9189", "uah": "0.4479"},
    {"date": "2025-02-25", "usd": "18.6520", "eur": "19.5268", "rub": "0.2121", "ron": "3.9234", "uah": "0.4469"},
    {"date": "2025-02-26", "usd": "18.6284", "eur": "19.5393", "rub": "0.2157", "ron": "3.9256", "uah": "0.4467"},
    {"date": "2025-02-27", "usd": "18.6233", "eur": "19.5358", "rub": "0.2163", "ron": "3.9248", "uah": "0.4474"},
    {"date": "2025-02-28", "usd": "18.6409", "eur": "19.5319", "rub": "0.2137", "ron": "3.9242", "uah": "0.4492"},
    {"date": "2025-03-01", "usd": "18.6409", "eur": "19.5319", "rub": "0.2137", "ron": "3.9242", "uah": "0.4492"},
    {"date": "2025-03-02", "usd": "18.6409", "eur": "19.5319", "rub": "0.2137", "ron": "3.9242", "uah": "0.4492"},
    {"date": "2025-03-03", "usd": "18.7667", "eur": "19.5146", "rub": "0.2119", "ron": "3.9214", "uah": "0.4530"},
    {"date": "2025-03-04", "usd": "18.6383", "eur": "19.4789", "rub": "0.2079", "ron": "3.9132", "uah": "0.4483"},
    {"date": "2025-03-05", "usd": "18.4449", "eur": "19.4446", "rub": "0.2069", "ron": "3.9069", "uah": "0.4435"},
    {"date": "2025-03-06", "usd": "18.2120", "eur": "19.4504", "rub": "0.2032", "ron": "3.9081", "uah": "0.4404"},
    {"date": "2025-03-07", "usd": "18.0588", "eur": "19.5035", "rub": "0.2019", "ron": "3.9194", "uah": "0.4377"},
    {"date": "2025-03-08", "usd": "18.0588", "eur": "19.5035", "rub": "0.2019", "ron": "3.9194", "uah": "0.4377"},
    {"date": "2025-03-09", "usd": "18.0588", "eur": "19.5035", "rub": "0.2019", "ron": "3.9194", "uah": "0.4377"},
    {"date": "2025-03-10", "usd": "18.0072", "eur": "19.5432", "rub": "0.2027", "ron": "3.9280", "uah": "0.4369"},
    {"date": "2025-03-11", "usd": "17.9895", "eur": "19.5240", "rub": "0.2047", "ron": "3.9230", "uah": "0.4354"},
    {"date": "2025-03-12", "usd": "17.8619", "eur": "19.4730", "rub": "0.2089", "ron": "3.9124", "uah": "0.4310"},
    {"date": "2025-03-13", "usd": "17.7785", "eur": "19.3803", "rub": "0.2048", "ron": "3.8937", "uah": "0.4280"},
    {"date": "2025-03-14", "usd": "17.8554", "eur": "19.3963", "rub": "0.2072", "ron": "3.8968", "uah": "0.4301"},
    {"date": "2025-03-15", "usd": "17.8554", "eur": "19.3963", "rub": "0.2072", "ron": "3.8968", "uah": "0.4301"},
    {"date": "2025-03-16", "usd": "17.8554", "eur": "19.3963", "rub": "0.2072", "ron": "3.8968", "uah": "0.4301"},
    {"date": "2025-03-17", "usd": "17.8486", "eur": "19.4461", "rub": "0.2092", "ron": "3.9074", "uah": "0.4301"},
    {"date": "2025-03-18", "usd": "17.8983", "eur": "19.5109", "rub": "0.2133", "ron": "3.9201", "uah": "0.4321"},
    {"date": "2025-03-19", "usd": "17.9199", "eur": "19.5650", "rub": "0.2196", "ron": "3.9305", "uah": "0.4312"},
    {"date": "2025-03-20", "usd": "17.9467", "eur": "19.5781", "rub": "0.2150", "ron": "3.9338", "uah": "0.4319"},
    {"date": "2025-03-21", "usd": "18.0450", "eur": "19.5752", "rub": "0.2142", "ron": "3.9334", "uah": "0.4345"},
    {"date": "2025-03-22", "usd": "18.0450", "eur": "19.5752", "rub": "0.2142", "ron": "3.9334", "uah": "0.4345"},
    {"date": "2025-03-23", "usd": "18.0450", "eur": "19.5752", "rub": "0.2142", "ron": "3.9334", "uah": "0.4345"},
    {"date": "2025-03-24", "usd": "18.0597", "eur": "19.5948", "rub": "0.2135", "ron": "3.9372", "uah": "0.4350"},
    {"date": "2025-03-25", "usd": "18.0629", "eur": "19.5712", "rub": "0.2136", "ron": "3.9328", "uah": "0.4337"},
    {"date": "2025-03-26", "usd": "18.0603", "eur": "19.5376", "rub": "0.2151", "ron": "3.9268", "uah": "0.4332"},
    {"date": "2025-03-27", "usd": "18.0864", "eur": "19.5207", "rub": "0.2151", "ron": "3.9229", "uah": "0.4352"},
    {"date": "2025-03-28", "usd": "18.0712", "eur": "19.4916", "rub": "0.2158", "ron": "3.9160", "uah": "0.4358"},
    {"date": "2025-03-29", "usd": "18.0712", "eur": "19.4916", "rub": "0.2158", "ron": "3.9160", "uah": "0.4358"},
    {"date": "2025-03-30", "usd": "18.0712", "eur": "19.4916", "rub": "0.2158", "ron": "3.9160", "uah": "0.4358"},
    {"date": "2025-03-31", "usd": "18.0491", "eur": "19.4461", "rub": "0.2154", "ron": "3.9067", "uah": "0.4352"},
    {"date": "2025-04-01", "usd": "17.9415", "eur": "19.4109", "rub": "0.2114", "ron": "3.8998", "uah": "0.4335"},
    {"date": "2025-04-02", "usd": "17.9740", "eur": "19.4119", "rub": "0.2118", "ron": "3.9001", "uah": "0.4342"},
    {"date": "2025-04-03", "usd": "17.9735", "eur": "19.4006", "rub": "0.2132", "ron": "3.8979", "uah": "0.4349"},
    {"date": "2025-04-04", "usd": "17.5664", "eur": "19.4144", "rub": "0.2088", "ron": "3.9004", "uah": "0.4246"},
    {"date": "2025-04-05", "usd": "17.5664", "eur": "19.4144", "rub": "0.2088", "ron": "3.9004", "uah": "0.4246"},
    {"date": "2025-04-06", "usd": "17.5664", "eur": "19.4144", "rub": "0.2088", "ron": "3.9004", "uah": "0.4246"},
    {"date": "2025-04-07", "usd": "17.7052", "eur": "19.5235", "rub": "0.2099", "ron": "3.9227", "uah": "0.4297"},
    {"date": "2025-04-08", "usd": "17.8222", "eur": "19.5349", "rub": "0.2069", "ron": "3.9248", "uah": "0.4337"},
    {"date": "2025-04-09", "usd": "17.8762", "eur": "19.5298", "rub": "0.2086", "ron": "3.9239", "uah": "0.4341"},
    {"date": "2025-04-10", "usd": "17.6808", "eur": "19.5046", "rub": "0.2057", "ron": "3.9186", "uah": "0.4283"},
    {"date": "2025-04-11", "usd": "17.6262", "eur": "19.5175", "rub": "0.2074", "ron": "3.9209", "uah": "0.4256"},
    {"date": "2025-04-12", "usd": "17.6262", "eur": "19.5175", "rub": "0.2074", "ron": "3.9209", "uah": "0.4256"},
    {"date": "2025-04-13", "usd": "17.6262", "eur": "19.5175", "rub": "0.2074", "ron": "3.9209", "uah": "0.4256"},
    {"date": "2025-04-14", "usd": "17.2458", "eur": "19.5395", "rub": "0.2032", "ron": "3.9254", "uah": "0.4167"},
    {"date": "2025-04-15", "usd": "17.2297", "eur": "19.6195", "rub": "0.2093", "ron": "3.9414", "uah": "0.4171"},
    {"date": "2025-04-16", "usd": "17.2927", "eur": "19.6151", "rub": "0.2104", "ron": "3.9406", "uah": "0.4200"},
    {"date": "2025-04-17", "usd": "17.2275", "eur": "19.5765", "rub": "0.2090", "ron": "3.9327", "uah": "0.4174"},
    {"date": "2025-04-18", "usd": "17.2236", "eur": "19.5660", "rub": "0.2087", "ron": "3.9307", "uah": "0.4161"},
    {"date": "2025-04-19", "usd": "17.2236", "eur": "19.5660", "rub": "0.2087", "ron": "3.9307", "uah": "0.4161"},
    {"date": "2025-04-20", "usd": "17.2236", "eur": "19.5660", "rub": "0.2087", "ron": "3.9307", "uah": "0.4161"},
    {"date": "2025-04-21", "usd": "17.2236", "eur": "19.5660", "rub": "0.2087", "ron": "3.9307", "uah": "0.4161"},
    {"date": "2025-04-22", "usd": "17.2496", "eur": "19.5955", "rub": "0.2090", "ron": "3.9366", "uah": "0.4167"},
    {"date": "2025-04-23", "usd": "17.0835", "eur": "19.6307", "rub": "0.2099", "ron": "3.9444", "uah": "0.4109"},
    {"date": "2025-04-24", "usd": "17.2154", "eur": "19.6273", "rub": "0.2087", "ron": "3.9434", "uah": "0.4123"},
    {"date": "2025-04-25", "usd": "17.2325", "eur": "19.6123", "rub": "0.2075", "ron": "3.9405", "uah": "0.4134"},
    {"date": "2025-04-26", "usd": "17.2325", "eur": "19.6123", "rub": "0.2075", "ron": "3.9405", "uah": "0.4134"},
    {"date": "2025-04-27", "usd": "17.2325", "eur": "19.6123", "rub": "0.2075", "ron": "3.9405", "uah": "0.4134"},
    {"date": "2025-04-28", "usd": "17.2325", "eur": "19.6123", "rub": "0.2075", "ron": "3.9405", "uah": "0.4134"},
    {"date": "2025-04-29", "usd": "17.2470", "eur": "19.5831", "rub": "0.2086", "ron": "3.9344", "uah": "0.4126"},
    {"date": "2025-04-30", "usd": "17.2034", "eur": "19.5706", "rub": "0.2107", "ron": "3.9317", "uah": "0.4143"},
    {"date": "2025-05-01", "usd": "17.2034", "eur": "19.5706", "rub": "0.2107", "ron": "3.9317", "uah": "0.4143"},
    {"date": "2025-05-02", "usd": "17.1865", "eur": "19.5290", "rub": "0.2109", "ron": "3.9229", "uah": "0.4143"},
    {"date": "2025-05-03", "usd": "17.1865", "eur": "19.5290", "rub": "0.2109", "ron": "3.9229", "uah": "0.4143"},
    {"date": "2025-05-04", "usd": "17.1865", "eur": "19.5290", "rub": "0.2109", "ron": "3.9229", "uah": "0.4143"},
    {"date": "2025-05-05", "usd": "17.2015", "eur": "19.4919", "rub": "0.2075", "ron": "3.9155", "uah": "0.4121"},
    {"date": "2025-05-06", "usd": "17.1490", "eur": "19.4530", "rub": "0.2125", "ron": "3.9074", "uah": "0.4124"},
    {"date": "2025-05-07", "usd": "17.1494", "eur": "19.4217", "rub": "0.2126", "ron": "3.8367", "uah": "0.4138"},
    {"date": "2025-05-08", "usd": "17.0909", "eur": "19.4229", "rub": "0.2109", "ron": "3.8080", "uah": "0.4125"},
    {"date": "2025-05-09", "usd": "17.0909", "eur": "19.4229", "rub": "0.2109", "ron": "3.8080", "uah": "0.4125"},
    {"date": "2025-05-10", "usd": "17.0909", "eur": "19.4229", "rub": "0.2109", "ron": "3.8080", "uah": "0.4125"},
    {"date": "2025-05-11", "usd": "17.0909", "eur": "19.4229", "rub": "0.2109", "ron": "3.8080", "uah": "0.4125"},
    {"date": "2025-05-12", "usd": "17.2258", "eur": "19.4445", "rub": "0.2089", "ron": "3.7949", "uah": "0.4147"},
    {"date": "2025-05-13", "usd": "17.5641", "eur": "19.4680", "rub": "0.2165", "ron": "3.8150", "uah": "0.4228"},
    {"date": "2025-05-14", "usd": "17.5006", "eur": "19.4327", "rub": "0.2174", "ron": "3.8073", "uah": "0.4221"},
    {"date": "2025-05-15", "usd": "17.3060", "eur": "19.4416", "rub": "0.2157", "ron": "3.8094", "uah": "0.4166"},
    {"date": "2025-05-16", "usd": "17.4379", "eur": "19.5305", "rub": "0.2165", "ron": "3.8249", "uah": "0.4206"},
    {"date": "2025-05-17", "usd": "17.4379", "eur": "19.5305", "rub": "0.2165", "ron": "3.8249", "uah": "0.4206"},
    {"date": "2025-05-18", "usd": "17.4379", "eur": "19.5305", "rub": "0.2165", "ron": "3.8249", "uah": "0.4206"},
    {"date": "2025-05-19", "usd": "17.4725", "eur": "19.5674", "rub": "0.2160", "ron": "3.8356", "uah": "0.4213"},
    {"date": "2025-05-20", "usd": "17.3146", "eur": "19.5361", "rub": "0.2158", "ron": "3.8808", "uah": "0.4164"},
    {"date": "2025-05-21", "usd": "17.3939", "eur": "19.5594", "rub": "0.2159", "ron": "3.8469", "uah": "0.4190"},
    {"date": "2025-05-22", "usd": "17.2751", "eur": "19.5900", "rub": "0.2153", "ron": "3.8635", "uah": "0.4169"},
    {"date": "2025-05-23", "usd": "17.3695", "eur": "19.6171", "rub": "0.2179", "ron": "3.8762", "uah": "0.4187"},
    {"date": "2025-05-24", "usd": "17.3695", "eur": "19.6171", "rub": "0.2179", "ron": "3.8762", "uah": "0.4187"},
    {"date": "2025-05-25", "usd": "17.3695", "eur": "19.6171", "rub": "0.2179", "ron": "3.8762", "uah": "0.4187"},
    {"date": "2025-05-26", "usd": "17.2974", "eur": "19.6291", "rub": "0.2176", "ron": "3.8839", "uah": "0.4168"},
    {"date": "2025-05-27", "usd": "17.2383", "eur": "19.6224", "rub": "0.2161", "ron": "3.8778", "uah": "0.4142"},
    {"date": "2025-05-28", "usd": "17.2907", "eur": "19.6111", "rub": "0.2162", "ron": "3.8755", "uah": "0.4148"},
    {"date": "2025-05-29", "usd": "17.2776", "eur": "19.5738", "rub": "0.2170", "ron": "3.8728", "uah": "0.4153"},
    {"date": "2025-05-30", "usd": "17.3250", "eur": "19.5547", "rub": "0.2207", "ron": "3.8650", "uah": "0.4172"},
    {"date": "2025-05-31", "usd": "17.3250", "eur": "19.5547", "rub": "0.2207", "ron": "3.8650", "uah": "0.4172"},
    {"date": "2025-06-01", "usd": "17.3250", "eur": "19.5547", "rub": "0.2207", "ron": "3.8650", "uah": "0.4172"},
    {"date": "2025-06-02", "usd": "17.3087", "eur": "19.6073", "rub": "0.2201", "ron": "3.8740", "uah": "0.4168"},
    {"date": "2025-06-03", "usd": "17.1880", "eur": "19.6218", "rub": "0.2169", "ron": "3.8820", "uah": "0.4126"},
    {"date": "2025-06-04", "usd": "17.2196", "eur": "19.6303", "rub": "0.2187", "ron": "3.8808", "uah": "0.4145"},
    {"date": "2025-06-05", "usd": "17.2279", "eur": "19.6071", "rub": "0.2193", "ron": "3.8794", "uah": "0.4156"},
    {"date": "2025-06-06", "usd": "17.1582", "eur": "19.6015", "rub": "0.2165", "ron": "3.8798", "uah": "0.4140"},
    {"date": "2025-06-07", "usd": "17.1582", "eur": "19.6015", "rub": "0.2165", "ron": "3.8798", "uah": "0.4140"},
    {"date": "2025-06-08", "usd": "17.1582", "eur": "19.6015", "rub": "0.2165", "ron": "3.8798", "uah": "0.4140"},
    {"date": "2025-06-09", "usd": "17.1948", "eur": "19.6416", "rub": "0.2167", "ron": "3.8950", "uah": "0.4153"},
    {"date": "2025-06-10", "usd": "17.2019", "eur": "19.6411", "rub": "0.2174", "ron": "3.8947", "uah": "0.4142"},
    {"date": "2025-06-11", "usd": "17.1847", "eur": "19.6301", "rub": "0.2186", "ron": "3.8981", "uah": "0.4135"},
    {"date": "2025-06-12", "usd": "17.1602", "eur": "19.6295", "rub": "0.2172", "ron": "3.9050", "uah": "0.4135"},
    {"date": "2025-06-13", "usd": "16.9489", "eur": "19.6489", "rub": "0.2114", "ron": "3.9072", "uah": "0.4086"},
    {"date": "2025-06-14", "usd": "16.9489", "eur": "19.6489", "rub": "0.2114", "ron": "3.9072", "uah": "0.4086"},
    {"date": "2025-06-15", "usd": "16.9489", "eur": "19.6489", "rub": "0.2114", "ron": "3.9072", "uah": "0.4086"},
    {"date": "2025-06-16", "usd": "17.1011", "eur": "19.6722", "rub": "0.2141", "ron": "3.9089", "uah": "0.4126"},
    {"date": "2025-06-17", "usd": "16.9923", "eur": "19.6703", "rub": "0.2158", "ron": "3.9115", "uah": "0.4089"},
    {"date": "2025-06-18", "usd": "17.0088", "eur": "19.6741", "rub": "0.2161", "ron": "3.9139", "uah": "0.4096"},
    {"date": "2025-06-19", "usd": "17.1331", "eur": "19.6928", "rub": "0.2185", "ron": "3.9145", "uah": "0.4110"},
    {"date": "2025-06-20", "usd": "17.1888", "eur": "19.7224", "rub": "0.2190", "ron": "3.9203", "uah": "0.4118"},
    {"date": "2025-06-21", "usd": "17.1888", "eur": "19.7224", "rub": "0.2190", "ron": "3.9203", "uah": "0.4118"},
    {"date": "2025-06-22", "usd": "17.1888", "eur": "19.7224", "rub": "0.2190", "ron": "3.9203", "uah": "0.4118"},
    {"date": "2025-06-23", "usd": "17.1270", "eur": "19.7371", "rub": "0.2187", "ron": "3.9209", "uah": "0.4088"},
    {"date": "2025-06-24", "usd": "17.2040", "eur": "19.7192", "rub": "0.2191", "ron": "3.9090", "uah": "0.4106"},
    {"date": "2025-06-25", "usd": "17.0055", "eur": "19.7213", "rub": "0.2165", "ron": "3.9069", "uah": "0.4073"},
    {"date": "2025-06-26", "usd": "16.9978", "eur": "19.7260", "rub": "0.2173", "ron": "3.9013", "uah": "0.4079"},
    {"date": "2025-06-27", "usd": "16.8382", "eur": "19.7260", "rub": "0.2150", "ron": "3.8908", "uah": "0.4049"},
    {"date": "2025-06-28", "usd": "16.8382", "eur": "19.7260", "rub": "0.2150", "ron": "3.8908", "uah": "0.4049"},
    {"date": "2025-06-29", "usd": "16.8382", "eur": "19.7260", "rub": "0.2150", "ron": "3.8908", "uah": "0.4049"},
    {"date": "2025-06-30", "usd": "16.8472", "eur": "19.7314", "rub": "0.2141", "ron": "3.8858", "uah": "0.4042"},
    {"date": "2025-07-01", "usd": "16.8172", "eur": "19.7148", "rub": "0.2140", "ron": "3.8847", "uah": "0.4025"},
    {"date": "2025-07-02", "usd": "16.6933", "eur": "19.7215", "rub": "0.2126", "ron": "3.8863", "uah": "0.3990"},
    {"date": "2025-07-03", "usd": "16.7896", "eur": "19.7563", "rub": "0.2133", "ron": "3.8999", "uah": "0.4022"},
    {"date": "2025-07-04", "usd": "16.7727", "eur": "19.7817", "rub": "0.2132", "ron": "3.9100", "uah": "0.4017"},
    {"date": "2025-07-05", "usd": "16.7727", "eur": "19.7817", "rub": "0.2132", "ron": "3.9100", "uah": "0.4017"},
    {"date": "2025-07-06", "usd": "16.7727", "eur": "19.7817", "rub": "0.2132", "ron": "3.9100", "uah": "0.4017"},
    {"date": "2025-07-07", "usd": "16.8157", "eur": "19.8038", "rub": "0.2133", "ron": "3.9145", "uah": "0.4029"},
    {"date": "2025-07-08", "usd": "16.9062", "eur": "19.8259", "rub": "0.2154", "ron": "3.9144", "uah": "0.4041"},
    {"date": "2025-07-09", "usd": "16.9042", "eur": "19.8269", "rub": "0.2166", "ron": "3.9124", "uah": "0.4048"},
    {"date": "2025-07-10", "usd": "16.9406", "eur": "19.8273", "rub": "0.2168", "ron": "3.9050", "uah": "0.4056"},
    {"date": "2025-07-11", "usd": "16.9133", "eur": "19.8376", "rub": "0.2175", "ron": "3.9072", "uah": "0.4042"},
    {"date": "2025-07-12", "usd": "16.9133", "eur": "19.8376", "rub": "0.2175", "ron": "3.9072", "uah": "0.4042"},
    {"date": "2025-07-13", "usd": "16.9133", "eur": "19.8376", "rub": "0.2175", "ron": "3.9072", "uah": "0.4042"},
    {"date": "2025-07-14", "usd": "16.9573", "eur": "19.8282", "rub": "0.2171", "ron": "3.9037", "uah": "0.4059"},
    {"date": "2025-07-15", "usd": "16.9370", "eur": "19.8027", "rub": "0.2164", "ron": "3.8982", "uah": "0.4049"},
    {"date": "2025-07-16", "usd": "16.9129", "eur": "19.7593", "rub": "0.2167", "ron": "3.8902", "uah": "0.4044"},
    {"date": "2025-07-17", "usd": "16.9984", "eur": "19.7479", "rub": "0.2176", "ron": "3.8938", "uah": "0.4062"},
    {"date": "2025-07-18", "usd": "17.0481", "eur": "19.7502", "rub": "0.2179", "ron": "3.8929", "uah": "0.4073"},
    {"date": "2025-07-19", "usd": "17.0481", "eur": "19.7502", "rub": "0.2179", "ron": "3.8929", "uah": "0.4073"},
    {"date": "2025-07-20", "usd": "17.0481", "eur": "19.7502", "rub": "0.2179", "ron": "3.8929", "uah": "0.4073"},
    {"date": "2025-07-21", "usd": "17.0068", "eur": "19.7942", "rub": "0.2165", "ron": "3.9019", "uah": "0.4073"},
    {"date": "2025-07-22", "usd": "17.0134", "eur": "19.8104", "rub": "0.2176", "ron": "3.9066", "uah": "0.4065"},
    {"date": "2025-07-23", "usd": "16.9261", "eur": "19.8052", "rub": "0.2161", "ron": "3.9064", "uah": "0.4052"},
    {"date": "2025-07-24", "usd": "16.8865", "eur": "19.8011", "rub": "0.2151", "ron": "3.9066", "uah": "0.4039"},
    {"date": "2025-07-25", "usd": "16.8430", "eur": "19.7871", "rub": "0.2122", "ron": "3.9026", "uah": "0.4032"},
    {"date": "2025-07-26", "usd": "16.8430", "eur": "19.7871", "rub": "0.2122", "ron": "3.9026", "uah": "0.4032"},
    {"date": "2025-07-27", "usd": "16.8430", "eur": "19.7871", "rub": "0.2122", "ron": "3.9026", "uah": "0.4032"},
    {"date": "2025-07-28", "usd": "16.8510", "eur": "19.7662", "rub": "0.2124", "ron": "3.8979", "uah": "0.4032"},
    {"date": "2025-07-29", "usd": "16.9569", "eur": "19.7700", "rub": "0.2121", "ron": "3.8992", "uah": "0.4055"},
    {"date": "2025-07-30", "usd": "17.0537", "eur": "19.7380", "rub": "0.2083", "ron": "3.8878", "uah": "0.4080"},
    {"date": "2025-07-31", "usd": "17.1046", "eur": "19.7404", "rub": "0.2092", "ron": "3.8891", "uah": "0.4097"},
    {"date": "2025-08-01", "usd": "17.2569", "eur": "19.7384", "rub": "0.2154", "ron": "3.8888", "uah": "0.4138"},
    {"date": "2025-08-02", "usd": "17.2569", "eur": "19.7384", "rub": "0.2154", "ron": "3.8888", "uah": "0.4138"},
    {"date": "2025-08-03", "usd": "17.2569", "eur": "19.7384", "rub": "0.2154", "ron": "3.8888", "uah": "0.4138"},
    {"date": "2025-08-04", "usd": "17.2927", "eur": "19.7362", "rub": "0.2153", "ron": "3.8897", "uah": "0.4139"},
    {"date": "2025-08-05", "usd": "17.0332", "eur": "19.7142", "rub": "0.2140", "ron": "3.8850", "uah": "0.4076"},
    {"date": "2025-08-06", "usd": "17.0658", "eur": "19.7008", "rub": "0.2131", "ron": "3.8822", "uah": "0.4094"},
    {"date": "2025-08-07", "usd": "16.9419", "eur": "19.6662", "rub": "0.2114", "ron": "3.8753", "uah": "0.4069"},
    {"date": "2025-08-08", "usd": "16.8292", "eur": "19.6397", "rub": "0.2114", "ron": "3.8712", "uah": "0.4061"},
    {"date": "2025-08-09", "usd": "16.8292", "eur": "19.6397", "rub": "0.2114", "ron": "3.8712", "uah": "0.4061"},
    {"date": "2025-08-10", "usd": "16.8292", "eur": "19.6397", "rub": "0.2114", "ron": "3.8712", "uah": "0.4061"},
    {"date": "2025-08-11", "usd": "16.8533", "eur": "19.6088", "rub": "0.2111", "ron": "3.8662", "uah": "0.4075"},
    {"date": "2025-08-12", "usd": "16.8113", "eur": "19.5801", "rub": "0.2107", "ron": "3.8649", "uah": "0.4055"},
    {"date": "2025-08-13", "usd": "16.8381", "eur": "19.5474", "rub": "0.2107", "ron": "3.8577", "uah": "0.4059"},
    {"date": "2025-08-14", "usd": "16.6478", "eur": "19.5079", "rub": "0.2086", "ron": "3.8531", "uah": "0.4009"},
    {"date": "2025-08-15", "usd": "16.6710", "eur": "19.4951", "rub": "0.2092", "ron": "3.8495", "uah": "0.4019"},
    {"date": "2025-08-16", "usd": "16.6710", "eur": "19.4951", "rub": "0.2092", "ron": "3.8495", "uah": "0.4019"},
    {"date": "2025-08-17", "usd": "16.6710", "eur": "19.4951", "rub": "0.2092", "ron": "3.8495", "uah": "0.4019"},
    {"date": "2025-08-18", "usd": "16.6648", "eur": "19.4761", "rub": "0.2088", "ron": "3.8470", "uah": "0.4038"},
    {"date": "2025-08-19", "usd": "16.6738", "eur": "19.4767", "rub": "0.2072", "ron": "3.8498", "uah": "0.4044"},
    {"date": "2025-08-20", "usd": "16.6998", "eur": "19.5170", "rub": "0.2067", "ron": "3.8582", "uah": "0.4036"},
    {"date": "2025-08-21", "usd": "16.7696", "eur": "19.5299", "rub": "0.2089", "ron": "3.8600", "uah": "0.4052"},
    {"date": "2025-08-22", "usd": "16.8081", "eur": "19.5814", "rub": "0.2086", "ron": "3.8733", "uah": "0.4080"},
    {"date": "2025-08-23", "usd": "16.8081", "eur": "19.5814", "rub": "0.2086", "ron": "3.8733", "uah": "0.4080"},
    {"date": "2025-08-24", "usd": "16.8081", "eur": "19.5814", "rub": "0.2086", "ron": "3.8733", "uah": "0.4080"},
    {"date": "2025-08-25", "usd": "16.8643", "eur": "19.5559", "rub": "0.2089", "ron": "3.8700", "uah": "0.4082"},
    {"date": "2025-08-26", "usd": "16.6883", "eur": "19.5036", "rub": "0.2061", "ron": "3.8593", "uah": "0.4025"},
    {"date": "2025-08-27", "usd": "16.6883", "eur": "19.5036", "rub": "0.2061", "ron": "3.8593", "uah": "0.4025"},
    {"date": "2025-08-28", "usd": "16.7240", "eur": "19.4734", "rub": "0.2075", "ron": "3.8518", "uah": "0.4039"},
    {"date": "2025-08-29", "usd": "16.6380", "eur": "19.4182", "rub": "0.2072", "ron": "3.8332", "uah": "0.4037"},
    {"date": "2025-08-30", "usd": "16.6380", "eur": "19.4182", "rub": "0.2072", "ron": "3.8332", "uah": "0.4037"},
    {"date": "2025-08-31", "usd": "16.6380", "eur": "19.4182", "rub": "0.2072", "ron": "3.8332", "uah": "0.4037"},
    {"date": "2025-09-01", "usd": "16.6352", "eur": "19.4083", "rub": "0.2062", "ron": "3.8261", "uah": "0.4023"},
    {"date": "2025-09-02", "usd": "16.5611", "eur": "19.4096", "rub": "0.2048", "ron": "3.8265", "uah": "0.4001"},
    {"date": "2025-09-03", "usd": "16.6938", "eur": "19.4182", "rub": "0.2070", "ron": "3.8220", "uah": "0.4037"},
    {"date": "2025-09-04", "usd": "16.6977", "eur": "19.4428", "rub": "0.2051", "ron": "3.8279", "uah": "0.4036"},
    {"date": "2025-09-05", "usd": "16.7187", "eur": "19.4840", "rub": "0.2051", "ron": "3.8381", "uah": "0.4047"},
    {"date": "2025-09-06", "usd": "16.7187", "eur": "19.4840", "rub": "0.2051", "ron": "3.8381", "uah": "0.4047"},
    {"date": "2025-09-07", "usd": "16.7187", "eur": "19.4840", "rub": "0.2051", "ron": "3.8381", "uah": "0.4047"},
    {"date": "2025-09-08", "usd": "16.6978", "eur": "19.5264", "rub": "0.2046", "ron": "3.8451", "uah": "0.4052"},
    {"date": "2025-09-09", "usd": "16.6883", "eur": "19.5704", "rub": "0.2032", "ron": "3.8586", "uah": "0.4045"},
    {"date": "2025-09-10", "usd": "16.6409", "eur": "19.5589", "rub": "0.1997", "ron": "3.8547", "uah": "0.4043"},
    {"date": "2025-09-11", "usd": "16.6846", "eur": "19.5218", "rub": "0.1964", "ron": "3.8478", "uah": "0.4046"},
    {"date": "2025-09-12", "usd": "16.6798", "eur": "19.4870", "rub": "0.1961", "ron": "3.8424", "uah": "0.4037"},
    {"date": "2025-09-13", "usd": "16.6798", "eur": "19.4870", "rub": "0.1961", "ron": "3.8424", "uah": "0.4037"},
    {"date": "2025-09-14", "usd": "16.6798", "eur": "19.4870", "rub": "0.1961", "ron": "3.8424", "uah": "0.4037"},
    {"date": "2025-09-15", "usd": "16.5879", "eur": "19.4642", "rub": "0.1993", "ron": "3.8389", "uah": "0.4017"},
    {"date": "2025-09-16", "usd": "16.5725", "eur": "19.4777", "rub": "0.2012", "ron": "3.8465", "uah": "0.4019"}
]